httpmedia/__init__.py
httpmedia/__main__.py
httpmedia/httpmedia.py
httpmedia/wsgi.py
httpmedia/static/baguetteBox.LICENSE
httpmedia/static/slideshow.js
httpmedia/static/style.css
httpmedia/static/vendor-baguetteBox.min.css
httpmedia/static/vendor-baguetteBox.min.js
httpmedia/static/water.min.css
httpmedia/static/water.min.css.LICENSE
httpmedia/views/base.tpl
httpmedia/views/links.tpl
httpmedia/views/slideshow_items.tpl
httpmedia-0.3.0.dist-info/METADATA
httpmedia-0.3.0.dist-info/WHEEL
httpmedia-0.3.0.dist-info/entry_points.txt
httpmedia-0.3.0.dist-info/licenses/COPYING.wtfpl
httpmedia-0.3.0.dist-info/RECORD
