Metadata-Version: 2.4
Name: httpmedia
Version: 0.3.0
Summary: httpmedia - HTTP file sharing with thumbnails
Project-URL: Homepage, https://gitlab.com/hydrargyrum/httpmedia
License-Expression: WTFPL
License-File: COPYING.wtfpl
Keywords: fileshare,http,thumbnail
Classifier: Development Status :: 4 - Beta
Classifier: Environment :: Web Environment
Classifier: Framework :: Bottle
Classifier: Intended Audience :: System Administrators
Classifier: License :: Public Domain
Classifier: Programming Language :: Python :: 3
Classifier: Programming Language :: Python :: 3.7
Classifier: Programming Language :: Python :: 3.8
Classifier: Programming Language :: Python :: 3.9
Classifier: Programming Language :: Python :: 3.10
Classifier: Programming Language :: Python :: 3.11
Classifier: Topic :: Communications :: File Sharing
Classifier: Topic :: Internet :: WWW/HTTP :: WSGI :: Application
Classifier: Topic :: Multimedia :: Graphics
Classifier: Topic :: Utilities
Requires-Python: >=3
Requires-Dist: bottle
Requires-Dist: pyjwt>=2
Requires-Dist: vignette[pillow]
